gitparent/__init__.py
gitparent/gitp.py
gitparent-20220727.dist-info/LICENSE
gitparent-20220727.dist-info/METADATA
gitparent-20220727.dist-info/WHEEL
gitparent-20220727.dist-info/entry_points.txt
gitparent-20220727.dist-info/top_level.txt
gitparent-20220727.dist-info/RECORD
