Metadata-Version: 2.1
Name: gitparent
Version: 20220727
Summary: Git Parent multirepo management utility
Home-page: https://github.com/gitparent/gitparent
Author: June Nguyen
Author-email: june@dreambigsemi.com
Project-URL: Bug Tracker, https://github.com/gitparent/gitparent/issues
Classifier: Programming Language :: Python :: 3
Classifier: Operating System :: OS Independent
Requires-Python: >=3.9
License-File: LICENSE
Requires-Dist: PyYAML (>=5.4.1)
Requires-Dist: filelock (>=3.0.12)
